s3i/__init__.py
s3i/broker.py
s3i/broker_message.py
s3i/callback_manager.py
s3i/config.py
s3i/directory.py
s3i/ditto_manager.py
s3i/event_system.py
s3i/exception.py
s3i/identity_provider.py
s3i/key_pgp.py
s3i/logger.py
s3i/repository.py
s3i/tools.py
s3i-0.7.6.dist-info/LICENSE.txt
s3i-0.7.6.dist-info/METADATA
s3i-0.7.6.dist-info/WHEEL
s3i-0.7.6.dist-info/top_level.txt
s3i-0.7.6.dist-info/RECORD
